README.txt
setup.py
collective/__init__.py
collective.collection.yearview.egg-info/PKG-INFO
collective.collection.yearview.egg-info/SOURCES.txt
collective.collection.yearview.egg-info/dependency_links.txt
collective.collection.yearview.egg-info/entry_points.txt
collective.collection.yearview.egg-info/namespace_packages.txt
collective.collection.yearview.egg-info/not-zip-safe
collective.collection.yearview.egg-info/requires.txt
collective.collection.yearview.egg-info/top_level.txt
collective/collection/__init__.py
collective/collection/yearview/__init__.py
collective/collection/yearview/configure.zcml
collective/collection/yearview/i18n.sh
collective/collection/yearview/tests.py
collective/collection/yearview/browser/__init__.py
collective/collection/yearview/browser/configure.zcml
collective/collection/yearview/browser/views.py
collective/collection/yearview/browser/year_view.pt
collective/collection/yearview/locales/collective.collection.yearview.pot
collective/collection/yearview/locales/manual.pot
collective/collection/yearview/locales/en/LC_MESSAGES/collective.collection.yearview.mo
collective/collection/yearview/locales/en/LC_MESSAGES/collective.collection.yearview.po
collective/collection/yearview/locales/fi/LC_MESSAGES/collective.collection.yearview.mo
collective/collection/yearview/locales/fi/LC_MESSAGES/collective.collection.yearview.po
collective/collection/yearview/profiles/default/metadata.xml
collective/collection/yearview/profiles/default/propertiestool.xml
collective/collection/yearview/profiles/default/types/Topic.xml
docs/HISTORY.txt
docs/INSTALL.txt
docs/LICENSE.GPL
docs/LICENSE.txt
docs/screenshot.png