Metadata-Version: 1.0
Name: collective.collection.yearview
Version: 1.0
Summary: Filter by year display for collection listings
Home-page: http://www.twinapex.com
Author: Mikko Ohtamaa
Author-email: mikko.ohtamaa@twinapex.fi
License: GPL
Keywords: plone collection year timeline
Platform: UNKNOWN
Classifier: Framework :: Plone
Classifier: Programming Language :: Python
Classifier: Topic :: Software Development :: Libraries :: Python Modules
